[
  {
    "changeType": "REMOVED",
    "date": "2026-03-10",
    "brand": "Nike",
    "style": "Mar 10 Zoom Vomero 5 Hyper Royal",
    "fieldChanged": "",
    "oldValue": "",
    "newValue": "",
    "detectedAt": "2026-03-11T06:09:39Z"
  },
  {
    "changeType": "REMOVED",
    "date": "2026-03-11",
    "brand": "Air Jordan",
    "style": "Air Jordan 1 Low OG Sail and Coconut Milk",
    "fieldChanged": "",
    "oldValue": "",
    "newValue": "",
    "detectedAt": "2026-03-11T06:09:39Z"
  },
  {
    "changeType": "REMOVED",
    "date": "2026-03-11",
    "brand": "Air Jordan",
    "style": "Air Jordan 13 Retro White and University Red",
    "fieldChanged": "",
    "oldValue": "",
    "newValue": "",
    "detectedAt": "2026-03-11T06:09:39Z"
  },
  {
    "changeType": "REMOVED",
    "date": "2026-03-11",
    "brand": "Air Jordan",
    "style": "Air Jordan 14 Retro Black and University Blue",
    "fieldChanged": "",
    "oldValue": "",
    "newValue": "",
    "detectedAt": "2026-03-11T06:09:39Z"
  },
  {
    "changeType": "REMOVED",
    "date": "2026-03-11",
    "brand": "Air Jordan",
    "style": "Air Jordan 3 x Teyana Taylor Concrete Rose",
    "fieldChanged": "",
    "oldValue": "",
    "newValue": "",
    "detectedAt": "2026-03-11T06:09:39Z"
  },
  {
    "changeType": "REMOVED",
    "date": "2026-03-11",
    "brand": "Air Jordan",
    "style": "Jordan x Teyana Taylor Apparel Collection",
    "fieldChanged": "",
    "oldValue": "",
    "newValue": "",
    "detectedAt": "2026-03-11T06:09:39Z"
  },
  {
    "changeType": "REMOVED",
    "date": "2026-03-11",
    "brand": "Nike",
    "style": "Kobe 3 Low Protro Pink Quartz",
    "fieldChanged": "",
    "oldValue": "",
    "newValue": "",
    "detectedAt": "2026-03-11T06:09:39Z"
  },
  {
    "changeType": "NEW",
    "date": "2026-03-12",
    "brand": "Air Jordan",
    "style": "Air Jordan 1 Low OG Sail and Coconut Milk",
    "fieldChanged": "",
    "oldValue": "",
    "newValue": "",
    "detectedAt": "2026-03-11T06:09:39Z"
  },
  {
    "changeType": "NEW",
    "date": "2026-03-12",
    "brand": "Air Jordan",
    "style": "Air Jordan 13 Retro White and University Red",
    "fieldChanged": "",
    "oldValue": "",
    "newValue": "",
    "detectedAt": "2026-03-11T06:09:39Z"
  },
  {
    "changeType": "NEW",
    "date": "2026-03-12",
    "brand": "Air Jordan",
    "style": "Air Jordan 14 Retro Black and University Blue",
    "fieldChanged": "",
    "oldValue": "",
    "newValue": "",
    "detectedAt": "2026-03-11T06:09:39Z"
  },
  {
    "changeType": "NEW",
    "date": "2026-03-12",
    "brand": "Air Jordan",
    "style": "Air Jordan 3 x Teyana Taylor Concrete Rose",
    "fieldChanged": "",
    "oldValue": "",
    "newValue": "",
    "detectedAt": "2026-03-11T06:09:39Z"
  },
  {
    "changeType": "NEW",
    "date": "2026-03-12",
    "brand": "Converse",
    "style": "Converse x Anonymous Club Chuck 70",
    "fieldChanged": "",
    "oldValue": "",
    "newValue": "",
    "detectedAt": "2026-03-11T06:09:39Z"
  },
  {
    "changeType": "NEW",
    "date": "2026-03-12",
    "brand": "Air Jordan",
    "style": "Jordan x Teyana Taylor Apparel Collection",
    "fieldChanged": "",
    "oldValue": "",
    "newValue": "",
    "detectedAt": "2026-03-11T06:09:39Z"
  },
  {
    "changeType": "NEW",
    "date": "2026-03-12",
    "brand": "Nike",
    "style": "Kobe 3 Low Protro Pink Quartz",
    "fieldChanged": "",
    "oldValue": "",
    "newValue": "",
    "detectedAt": "2026-03-11T06:09:39Z"
  },
  {
    "changeType": "RETAIL_CHANGED",
    "date": "2026-03-12",
    "brand": "Nike",
    "style": "Nike Sabrina 3 Oregon Ducks",
    "fieldChanged": "retailPrice",
    "oldValue": 399,
    "newValue": 0,
    "detectedAt": "2026-03-11T06:09:39Z"
  },
  {
    "changeType": "NEW",
    "date": "2026-03-13",
    "brand": "Converse",
    "style": "Converse Kentucky Wildcats 30th Anniversary",
    "fieldChanged": "",
    "oldValue": "",
    "newValue": "",
    "detectedAt": "2026-03-11T06:09:39Z"
  },
  {
    "changeType": "NEW",
    "date": "2026-03-13",
    "brand": "Reebok",
    "style": "Reebok Angel Navy Halo",
    "fieldChanged": "",
    "oldValue": "",
    "newValue": "",
    "detectedAt": "2026-03-11T06:09:39Z"
  },
  {
    "changeType": "REMOVED",
    "date": "2026-03-13",
    "brand": "Nike",
    "style": "Mar 13 Kobe 3 Low Protro Pink Quartz",
    "fieldChanged": "",
    "oldValue": "",
    "newValue": "",
    "detectedAt": "2026-03-11T06:09:39Z"
  },
  {
    "changeType": "RETAIL_CHANGED",
    "date": "2026-03-14",
    "brand": "Air Jordan",
    "style": "Air Jordan 13 Chicago",
    "fieldChanged": "retailPrice",
    "oldValue": 375,
    "newValue": 0,
    "detectedAt": "2026-03-11T06:09:39Z"
  },
  {
    "changeType": "NEW",
    "date": "2026-03-17",
    "brand": "Converse",
    "style": "Mar 17 Converse x Anonymous Club Chuck 70",
    "fieldChanged": "",
    "oldValue": "",
    "newValue": "",
    "detectedAt": "2026-03-11T06:09:39Z"
  },
  {
    "changeType": "REMOVED",
    "date": "2026-03-18",
    "brand": "Air Jordan",
    "style": "Mar 18 Air Jordan 1 Low OG Sail and Coconut Milk",
    "fieldChanged": "",
    "oldValue": "",
    "newValue": "",
    "detectedAt": "2026-03-11T06:09:39Z"
  },
  {
    "changeType": "RETAIL_CHANGED",
    "date": "2026-03-18",
    "brand": "Air Jordan",
    "style": "Air Jordan 1 Low OG Sail / Off White",
    "fieldChanged": "retailPrice",
    "oldValue": 329,
    "newValue": 0,
    "detectedAt": "2026-03-11T06:09:39Z"
  },
  {
    "changeType": "NEW",
    "date": "2026-03-19",
    "brand": "Nike",
    "style": "Nike GT Future Unseen Hours",
    "fieldChanged": "",
    "oldValue": "",
    "newValue": "",
    "detectedAt": "2026-03-11T06:09:39Z"
  },
  {
    "changeType": "REMOVED",
    "date": "2026-03-19",
    "brand": "Nike",
    "style": "Nike G.t. Cut 1 Orange Pulse / Persian Violet",
    "fieldChanged": "",
    "oldValue": "",
    "newValue": "",
    "detectedAt": "2026-03-11T06:09:39Z"
  },
  {
    "changeType": "REMOVED",
    "date": "2026-03-19",
    "brand": "Nike",
    "style": "Nike G.t. Future Unseen Hours",
    "fieldChanged": "",
    "oldValue": "",
    "newValue": "",
    "detectedAt": "2026-03-11T06:09:39Z"
  }
]